pelican_githubprojects/github.py
pelican_githubprojects/__init__.py
pelican_githubprojects-0.1.1.dist-info/zip-safe
pelican_githubprojects-0.1.1.dist-info/DESCRIPTION.rst
pelican_githubprojects-0.1.1.dist-info/RECORD
pelican_githubprojects-0.1.1.dist-info/METADATA
pelican_githubprojects-0.1.1.dist-info/metadata.json
pelican_githubprojects-0.1.1.dist-info/WHEEL
pelican_githubprojects-0.1.1.dist-info/top_level.txt
